Backtest_app/__init__.py
Backtest_app/app.py
flask_app/Data_treated/vol_surface_Euro Stoxx 50_2024-09-30_17-11.xlsx
flask_app/Data_treated/vol_surface_Euro Stoxx 50_2024-09-30_22-10.xlsx
flask_app/Data_treated/vol_surface_Euro Stoxx 50_2024-10-01_00-11.xlsx
flask_app/Data_treated/vol_surface_Euro Stoxx 50_2024-10-01_01-24.xlsx
flask_app/Data_treated/vol_surface_Euro Stoxx 50_2024-10-01_17-23.xlsx
flask_app/Data_treated/vol_surface_Euro Stoxx 50_2024-10-01_18-08.xlsx
flask_app/Data_treated/vol_surface_Euro Stoxx 50_2024-10-01_18-10.xlsx
flask_app/Data_treated/vol_surface_Euro Stoxx 50_2024-10-03_10-31.xlsx
flask_app/Data_treated/vol_surface_Euro Stoxx 50_2024-10-03_15-05.xlsx
flask_app/Data_treated/vol_surface_Euro Stoxx 50_2024-10-04_10-50.xlsx
flask_app/Data_treated/vol_surface_Euro Stoxx 50_2024-10-04_13-53.xlsx
flask_app/Data_treated/vol_surface_Euro Stoxx 50_2024-10-04_21-51.xlsx
flask_app/Data_treated/vol_surface_Euro Stoxx 50_2024-10-07_19-51.xlsx
flask_app/Data_treated/vol_surface_Euro Stoxx 50_2024-10-07_21-44.xlsx
flask_app/Data_treated/vol_surface_Euro Stoxx 50_2024-10-07_23-10.xlsx
flask_app/Data_treated/vol_surface_Euro Stoxx 50_2024-10-08_12-25.xlsx
flask_app/Data_treated/vol_surface_Euro Stoxx 50_2024-10-08_17-35.xlsx
flask_app/Data_treated/vol_surface_Euro Stoxx 50_2024-10-08_20-43.xlsx
flask_app/Data_treated/vol_surface_Euro Stoxx 50_2024-10-08_21-33.xlsx
flask_app/Data_treated/vol_surface_Euro Stoxx 50_2024-10-08_21-34.xlsx
flask_app/Data_treated/vol_surface_Euro Stoxx 50_2024-10-08_21-37.xlsx
flask_app/Data_treated/vol_surface_Euro Stoxx 50_2024-10-08_21-40.xlsx
flask_app/Data_treated/vol_surface_Euro Stoxx 50_2024-10-08_21-46.xlsx
flask_app/Data_treated/vol_surface_Euro Stoxx 50_2024-10-08_22-09.xlsx
flask_app/Data_treated/vol_surface_Euro Stoxx 50_2024-10-08_22-10.xlsx
flask_app/Data_treated/vol_surface_Euro Stoxx 50_2024-10-08_22-11.xlsx
flask_app/Data_treated/vol_surface_Euro Stoxx 50_2024-10-08_22-12.xlsx
pybacktestchain_vol_cash-0.0.9.dist-info/LICENSE
pybacktestchain_vol_cash-0.0.9.dist-info/METADATA
pybacktestchain_vol_cash-0.0.9.dist-info/WHEEL
pybacktestchain_vol_cash-0.0.9.dist-info/RECORD
